{"status":"success","data":{"activeTargets":[{"discoveredLabels":{"__address__":"grafana:3000","__metrics_path__":"/metrics","__scheme__":"http","__scrape_interval__":"15s","__scrape_timeout__":"10s","environment":"monitoring","job":"grafana","service":"grafana"},"labels":{"environment":"monitoring","instance":"grafana:3000","job":"grafana","service":"grafana"},"scrapePool":"grafana","scrapeUrl":"http://grafana:3000/metrics","globalUrl":"http://grafana:3000/metrics","lastError":"","lastScrape":"2026-05-06T18:05:44.728203429Z","lastScrapeDuration":0.036078118,"health":"up","scrapeInterval":"15s","scrapeTimeout":"10s"},{"discoveredLabels":{"__address__":"loki:3100","__metrics_path__":"/metrics","__scheme__":"http","__scrape_interval__":"15s","__scrape_timeout__":"10s","environment":"monitoring","job":"loki","service":"loki"},"labels":{"environment":"monitoring","instance":"loki:3100","job":"loki","service":"loki"},"scrapePool":"loki","scrapeUrl":"http://loki:3100/metrics","globalUrl":"http://loki:3100/metrics","lastError":"","lastScrape":"2026-05-06T18:05:39.524707668Z","lastScrapeDuration":0.018344347,"health":"up","scrapeInterval":"15s","scrapeTimeout":"10s"},{"discoveredLabels":{"__address__":"localhost:9090","__metrics_path__":"/metrics","__scheme__":"http","__scrape_interval__":"15s","__scrape_timeout__":"10s","environment":"monitoring","job":"prometheus","service":"prometheus"},"labels":{"environment":"monitoring","instance":"localhost:9090","job":"prometheus","service":"prometheus"},"scrapePool":"prometheus","scrapeUrl":"http://localhost:9090/metrics","globalUrl":"http://4d51d23309fa:9090/metrics","lastError":"","lastScrape":"2026-05-06T18:05:47.968120584Z","lastScrapeDuration":0.013923515,"health":"up","scrapeInterval":"15s","scrapeTimeout":"10s"}],"droppedTargets":[],"droppedTargetCounts":{"grafana":0,"loki":0,"prometheus":0}}}
